{
  "classname": null,
  "name": null,
  "animation": {
    "classname": null,
    "name": "AnimationManager",
    "actionlist": []
  },
  "dataScale": 1,
  "designHeight": 1080,
  "designWidth": 1920,
  "textures": [],
  "texturesPng": [],
  "version": "1.6.0.0",
  "widgetTree": {
    "classname": "Panel",
    "name": null,
    "children": [
      {
        "classname": "Panel",
        "name": null,
        "children": [
          {
            "classname": "ImageView",
            "name": null,
            "children": [],
            "options": {
              "__type": "ImageViewSurrogate:#EditorCommon.JsonModel.Component.GUI",
              "classname": "ImageView",
              "name": "title",
              "ZOrder": 0,
              "actiontag": 11528032,
              "anchorPointX": 0.5,
              "anchorPointY": 0.5,
              "classType": "CocoStudio.EngineAdapterWrap.CSImageView",
              "colorB": 255,
              "colorG": 255,
              "colorR": 255,
              "customProperty": "",
              "flipX": false,
              "flipY": false,
              "height": 206,
              "ignoreSize": true,
              "layoutParameter": {
                "classname": null,
                "name": null,
                "align": 8,
                "gravity": 0,
                "layoutEageType": 0,
                "layoutNormalHorizontal": 0,
                "layoutNormalVertical": 0,
                "layoutParentHorizontal": 0,
                "layoutParentVertical": 0,
                "marginDown": 592,
                "marginLeft": 0,
                "marginRight": 0,
                "marginTop": 0,
                "relativeName": "title",
                "relativeToName": "pop",
                "type": 2
              },
              "opacity": 255,
              "positionPercentX": 0.5,
              "positionPercentY": 0.9612725,
              "positionType": 0,
              "rotation": 0,
              "scaleX": 1,
              "scaleY": 1,
              "sizePercentX": 0.725402534,
              "sizePercentY": 0.284923941,
              "sizeType": 0,
              "tag": 3,
              "touchAble": false,
              "useMergedTexture": false,
              "visible": true,
              "width": 811,
              "x": 559,
              "y": 695,
              "capInsetsHeight": 1,
              "capInsetsWidth": 1,
              "capInsetsX": 0,
              "capInsetsY": 0,
              "fileName": null,
              "fileNameData": {
                "path": "install/top_ziyuan.png",
                "plistFile": "",
                "resourceType": 0
              },
              "scale9Enable": false,
              "scale9Height": 206,
              "scale9Width": 811
            }
          },
          {
            "classname": "Panel",
            "name": null,
            "children": [
              {
                "classname": "ImageView",
                "name": null,
                "children": [],
                "options": {
                  "__type": "ImageViewSurrogate:#EditorCommon.JsonModel.Component.GUI",
                  "classname": "ImageView",
                  "name": "progress_bg",
                  "ZOrder": 1,
                  "actiontag": 36633691,
                  "anchorPointX": 0.5,
                  "anchorPointY": 0.5,
                  "classType": "CocoStudio.EngineAdapterWrap.CSImageView",
                  "colorB": 255,
                  "colorG": 255,
                  "colorR": 255,
                  "customProperty": "",
                  "flipX": false,
                  "flipY": false,
                  "height": 44,
                  "ignoreSize": true,
                  "layoutParameter": {
                    "classname": null,
                    "name": null,
                    "align": 5,
                    "gravity": 0,
                    "layoutEageType": 0,
                    "layoutNormalHorizontal": 0,
                    "layoutNormalVertical": 0,
                    "layoutParentHorizontal": 0,
                    "layoutParentVertical": 0,
                    "marginDown": 0,
                    "marginLeft": 0,
                    "marginRight": 0,
                    "marginTop": 0,
                    "relativeName": "progress_bg",
                    "relativeToName": "progress_panel",
                    "type": 2
                  },
                  "opacity": 255,
                  "positionPercentX": 0.5,
                  "positionPercentY": 0.5,
                  "positionType": 0,
                  "rotation": 0,
                  "scaleX": 1,
                  "scaleY": 1,
                  "sizePercentX": 0.7777778,
                  "sizePercentY": 0.11,
                  "sizeType": 0,
                  "tag": 15,
                  "touchAble": false,
                  "useMergedTexture": false,
                  "visible": true,
                  "width": 700,
                  "x": 450,
                  "y": 200,
                  "capInsetsHeight": 1,
                  "capInsetsWidth": 1,
                  "capInsetsX": 0,
                  "capInsetsY": 0,
                  "fileName": null,
                  "fileNameData": {
                    "path": "install/img_loading_bg.png",
                    "plistFile": "",
                    "resourceType": 0
                  },
                  "scale9Enable": false,
                  "scale9Height": 44,
                  "scale9Width": 700
                }
              },
              {
                "classname": "LoadingBar",
                "name": null,
                "children": [],
                "options": {
                  "__type": "LoadingBarSurrogate:#EditorCommon.JsonModel.Component.GUI",
                  "classname": "LoadingBar",
                  "name": "progress",
                  "ZOrder": 1,
                  "actiontag": 19556926,
                  "anchorPointX": 0.5,
                  "anchorPointY": 0.5,
                  "classType": "CocoStudio.EngineAdapterWrap.CSLoadingBar",
                  "colorB": 255,
                  "colorG": 255,
                  "colorR": 255,
                  "customProperty": "",
                  "flipX": false,
                  "flipY": false,
                  "height": 44,
                  "ignoreSize": true,
                  "layoutParameter": {
                    "classname": null,
                    "name": null,
                    "align": 5,
                    "gravity": 0,
                    "layoutEageType": 0,
                    "layoutNormalHorizontal": 0,
                    "layoutNormalVertical": 0,
                    "layoutParentHorizontal": 0,
                    "layoutParentVertical": 0,
                    "marginDown": 0,
                    "marginLeft": 0,
                    "marginRight": 0,
                    "marginTop": 0,
                    "relativeName": "progress",
                    "relativeToName": "progress_panel",
                    "type": 2
                  },
                  "opacity": 255,
                  "positionPercentX": 0.5,
                  "positionPercentY": 0.5,
                  "positionType": 0,
                  "rotation": 0,
                  "scaleX": 1,
                  "scaleY": 1,
                  "sizePercentX": 0.7777778,
                  "sizePercentY": 0.11,
                  "sizeType": 0,
                  "tag": 16,
                  "touchAble": false,
                  "useMergedTexture": false,
                  "visible": true,
                  "width": 700,
                  "x": 450,
                  "y": 200,
                  "capInsetsHeight": 1,
                  "capInsetsWidth": 1,
                  "capInsetsX": 0,
                  "capInsetsY": 0,
                  "direction": 0,
                  "percent": 0,
                  "scale9Enable": false,
                  "texture": null,
                  "textureData": {
                    "path": "install/loadingbar.png",
                    "plistFile": "",
                    "resourceType": 0
                  }
                }
              },
              {
                "classname": "ImageView",
                "name": null,
                "children": [],
                "options": {
                  "__type": "ImageViewSurrogate:#EditorCommon.JsonModel.Component.GUI",
                  "classname": "ImageView",
                  "name": "progress_back",
                  "ZOrder": 0,
                  "actiontag": 36233478,
                  "anchorPointX": 0.5,
                  "anchorPointY": 0.5,
                  "classType": "CocoStudio.EngineAdapterWrap.CSImageView",
                  "colorB": 255,
                  "colorG": 255,
                  "colorR": 255,
                  "customProperty": "",
                  "flipX": false,
                  "flipY": false,
                  "height": 148,
                  "ignoreSize": true,
                  "layoutParameter": {
                    "classname": null,
                    "name": null,
                    "align": 5,
                    "gravity": 0,
                    "layoutEageType": 0,
                    "layoutNormalHorizontal": 0,
                    "layoutNormalVertical": 0,
                    "layoutParentHorizontal": 0,
                    "layoutParentVertical": 0,
                    "marginDown": 0,
                    "marginLeft": 0,
                    "marginRight": 0,
                    "marginTop": 0,
                    "relativeName": "progress_back",
                    "relativeToName": "progress_panel",
                    "type": 2
                  },
                  "opacity": 255,
                  "positionPercentX": 0.5,
                  "positionPercentY": 0.5,
                  "positionType": 0,
                  "rotation": 0,
                  "scaleX": 1,
                  "scaleY": 1,
                  "sizePercentX": 0.08888889,
                  "sizePercentY": 0.2,
                  "sizeType": 0,
                  "tag": 20,
                  "touchAble": false,
                  "useMergedTexture": false,
                  "visible": true,
                  "width": 793,
                  "x": 450,
                  "y": 200,
                  "capInsetsHeight": 1,
                  "capInsetsWidth": 1,
                  "capInsetsX": 0,
                  "capInsetsY": 0,
                  "fileName": null,
                  "fileNameData": {
                    "path": "install/ddd_kuang.png",
                    "plistFile": "",
                    "resourceType": 0
                  },
                  "scale9Enable": false,
                  "scale9Height": 148,
                  "scale9Width": 793
                }
              },
              {
                "classname": "ImageView",
                "name": null,
                "children": [],
                "options": {
                  "__type": "ImageViewSurrogate:#EditorCommon.JsonModel.Component.GUI",
                  "classname": "ImageView",
                  "name": "ing",
                  "ZOrder": 0,
                  "actiontag": 15229682,
                  "anchorPointX": 0.5,
                  "anchorPointY": 0.5,
                  "classType": "CocoStudio.EngineAdapterWrap.CSImageView",
                  "colorB": 255,
                  "colorG": 255,
                  "colorR": 255,
                  "customProperty": "",
                  "flipX": false,
                  "flipY": false,
                  "height": 34,
                  "ignoreSize": true,
                  "layoutParameter": {
                    "classname": null,
                    "name": null,
                    "align": 8,
                    "gravity": 0,
                    "layoutEageType": 0,
                    "layoutNormalHorizontal": 0,
                    "layoutNormalVertical": 0,
                    "layoutParentHorizontal": 0,
                    "layoutParentVertical": 0,
                    "marginDown": 52,
                    "marginLeft": 0,
                    "marginRight": 0,
                    "marginTop": 0,
                    "relativeName": "ing",
                    "relativeToName": "progress_panel",
                    "type": 2
                  },
                  "opacity": 255,
                  "positionPercentX": 0.5,
                  "positionPercentY": 0.1725,
                  "positionType": 0,
                  "rotation": 0,
                  "scaleX": 1,
                  "scaleY": 1,
                  "sizePercentX": 0.08888889,
                  "sizePercentY": 0.2,
                  "sizeType": 0,
                  "tag": 21,
                  "touchAble": false,
                  "useMergedTexture": false,
                  "visible": true,
                  "width": 329,
                  "x": 450,
                  "y": 69,
                  "capInsetsHeight": 1,
                  "capInsetsWidth": 1,
                  "capInsetsX": 0,
                  "capInsetsY": 0,
                  "fileName": null,
                  "fileNameData": {
                    "path": "install/tishi_jiazai.png",
                    "plistFile": "",
                    "resourceType": 0
                  },
                  "scale9Enable": false,
                  "scale9Height": 34,
                  "scale9Width": 329
                }
              },
              {
                "classname": "ImageView",
                "name": null,
                "children": [],
                "options": {
                  "__type": "ImageViewSurrogate:#EditorCommon.JsonModel.Component.GUI",
                  "classname": "ImageView",
                  "name": "percent",
                  "ZOrder": 0,
                  "actiontag": 46885581,
                  "anchorPointX": 0.5,
                  "anchorPointY": 0.5,
                  "classType": "CocoStudio.EngineAdapterWrap.CSImageView",
                  "colorB": 255,
                  "colorG": 255,
                  "colorR": 255,
                  "customProperty": "",
                  "flipX": false,
                  "flipY": false,
                  "height": 43,
                  "ignoreSize": true,
                  "layoutParameter": {
                    "classname": null,
                    "name": null,
                    "align": 3,
                    "gravity": 0,
                    "layoutEageType": 0,
                    "layoutNormalHorizontal": 0,
                    "layoutNormalVertical": 0,
                    "layoutParentHorizontal": 0,
                    "layoutParentVertical": 0,
                    "marginDown": 0,
                    "marginLeft": 0,
                    "marginRight": 371,
                    "marginTop": 54,
                    "relativeName": "percent",
                    "relativeToName": "progress_panel",
                    "type": 2
                  },
                  "opacity": 255,
                  "positionPercentX": 0.566666663,
                  "positionPercentY": 0.81125,
                  "positionType": 0,
                  "rotation": 0,
                  "scaleX": 1,
                  "scaleY": 1,
                  "sizePercentX": 0.08888889,
                  "sizePercentY": 0.2,
                  "sizeType": 0,
                  "tag": 22,
                  "touchAble": false,
                  "useMergedTexture": false,
                  "visible": true,
                  "width": 38,
                  "x": 510,
                  "y": 324,
                  "capInsetsHeight": 1,
                  "capInsetsWidth": 1,
                  "capInsetsX": 0,
                  "capInsetsY": 0,
                  "fileName": null,
                  "fileNameData": {
                    "path": "install/bfz_fuhao.png",
                    "plistFile": "",
                    "resourceType": 0
                  },
                  "scale9Enable": false,
                  "scale9Height": 43,
                  "scale9Width": 38
                }
              },
              {
                "classname": "LabelBMFont",
                "name": null,
                "children": [],
                "options": {
                  "__type": "LabelBMFontSurrogate:#EditorCommon.JsonModel.Component.GUI",
                  "classname": "LabelBMFont",
                  "name": "num",
                  "ZOrder": 0,
                  "actiontag": 46510996,
                  "anchorPointX": 0.5,
                  "anchorPointY": 0.5,
                  "classType": "CocoStudio.EngineAdapterWrap.CSLabelBMFont",
                  "colorB": 255,
                  "colorG": 255,
                  "colorR": 255,
                  "customProperty": "",
                  "flipX": false,
                  "flipY": false,
                  "height": 50,
                  "ignoreSize": true,
                  "layoutParameter": {
                    "classname": null,
                    "name": null,
                    "align": 2,
                    "gravity": 0,
                    "layoutEageType": 0,
                    "layoutNormalHorizontal": 0,
                    "layoutNormalVertical": 0,
                    "layoutParentHorizontal": 0,
                    "layoutParentVertical": 0,
                    "marginDown": 0,
                    "marginLeft": 429,
                    "marginRight": 0,
                    "marginTop": 48,
                    "relativeName": "num",
                    "relativeToName": "progress_panel",
                    "type": 2
                  },
                  "opacity": 255,
                  "positionPercentX": 0.5,
                  "positionPercentY": 0.8175,
                  "positionType": 0,
                  "rotation": 0,
                  "scaleX": 1,
                  "scaleY": 1,
                  "sizePercentX": 0.2611111,
                  "sizePercentY": 0.0925,
                  "sizeType": 0,
                  "tag": 23,
                  "touchAble": false,
                  "useMergedTexture": false,
                  "visible": true,
                  "width": 66,
                  "x": 450,
                  "y": 327,
                  "fileNameData": {
                    "path": "install/xzjd_shuzi-export.fnt",
                    "plistFile": "",
                    "resourceType": 0
                  },
                  "text": "90"
                }
              }
            ],
            "options": {
              "__type": "PanelSurrogate:#EditorCommon.JsonModel.Component.GUI",
              "classname": "Panel",
              "name": "progress_panel",
              "ZOrder": 0,
              "actiontag": 10594405,
              "anchorPointX": 0,
              "anchorPointY": 0,
              "classType": "CocoStudio.EngineAdapterWrap.CSPanel",
              "colorB": 255,
              "colorG": 255,
              "colorR": 255,
              "customProperty": "",
              "flipX": false,
              "flipY": false,
              "height": 400,
              "ignoreSize": false,
              "layoutParameter": {
                "classname": null,
                "name": null,
                "align": 5,
                "gravity": 0,
                "layoutEageType": 0,
                "layoutNormalHorizontal": 0,
                "layoutNormalVertical": 0,
                "layoutParentHorizontal": 0,
                "layoutParentVertical": 0,
                "marginDown": 0,
                "marginLeft": 0,
                "marginRight": 0,
                "marginTop": 0,
                "relativeName": "progress_panel",
                "relativeToName": "pop",
                "type": 2
              },
              "opacity": 255,
              "positionPercentX": 0.0974955261,
              "positionPercentY": 0.223374829,
              "positionType": 0,
              "rotation": 0,
              "scaleX": 1,
              "scaleY": 1,
              "sizePercentX": 0.805008948,
              "sizePercentY": 0.5532504,
              "sizeType": 0,
              "tag": 12,
              "touchAble": true,
              "useMergedTexture": false,
              "visible": false,
              "width": 900,
              "x": 109,
              "y": 161,
              "adaptScreen": false,
              "backGroundImage": null,
              "backGroundImageData": null,
              "backGroundScale9Enable": false,
              "bgColorB": 255,
              "bgColorG": 200,
              "bgColorOpacity": 0,
              "bgColorR": 150,
              "bgEndColorB": 255,
              "bgEndColorG": 200,
              "bgEndColorR": 150,
              "bgStartColorB": 255,
              "bgStartColorG": 255,
              "bgStartColorR": 255,
              "capInsetsHeight": 1,
              "capInsetsWidth": 1,
              "capInsetsX": 0,
              "capInsetsY": 0,
              "clipAble": false,
              "colorType": 1,
              "layoutType": 3,
              "vectorX": 0,
              "vectorY": -0.5
            }
          },
          {
            "classname": "Panel",
            "name": null,
            "children": [
              {
                "classname": "ImageView",
                "name": null,
                "children": [],
                "options": {
                  "__type": "ImageViewSurrogate:#EditorCommon.JsonModel.Component.GUI",
                  "classname": "ImageView",
                  "name": "down_img",
                  "ZOrder": 0,
                  "actiontag": 33895468,
                  "anchorPointX": 0.5,
                  "anchorPointY": 0.5,
                  "classType": "CocoStudio.EngineAdapterWrap.CSImageView",
                  "colorB": 255,
                  "colorG": 255,
                  "colorR": 255,
                  "customProperty": "",
                  "flipX": false,
                  "flipY": false,
                  "height": 233,
                  "ignoreSize": true,
                  "layoutParameter": {
                    "classname": null,
                    "name": null,
                    "align": 1,
                    "gravity": 0,
                    "layoutEageType": 0,
                    "layoutNormalHorizontal": 0,
                    "layoutNormalVertical": 0,
                    "layoutParentHorizontal": 0,
                    "layoutParentVertical": 0,
                    "marginDown": 0,
                    "marginLeft": 51,
                    "marginRight": 0,
                    "marginTop": 83,
                    "relativeName": "down_img",
                    "relativeToName": "if_install",
                    "type": 2
                  },
                  "opacity": 255,
                  "positionPercentX": 0.147,
                  "positionPercentY": 0.5566667,
                  "positionType": 0,
                  "rotation": 0,
                  "scaleX": 1,
                  "scaleY": 1,
                  "sizePercentX": 0.192,
                  "sizePercentY": 0.5177778,
                  "sizeType": 0,
                  "tag": 4,
                  "touchAble": false,
                  "useMergedTexture": false,
                  "visible": true,
                  "width": 192,
                  "x": 147,
                  "y": 250,
                  "capInsetsHeight": 1,
                  "capInsetsWidth": 1,
                  "capInsetsX": 0,
                  "capInsetsY": 0,
                  "fileName": null,
                  "fileNameData": {
                    "path": "install/ziyuan_tubiao.png",
                    "plistFile": "",
                    "resourceType": 0
                  },
                  "scale9Enable": false,
                  "scale9Height": 233,
                  "scale9Width": 192
                }
              },
              {
                "classname": "Label",
                "name": null,
                "children": [],
                "options": {
                  "__type": "LabelSurrogate:#EditorCommon.JsonModel.Component.GUI",
                  "classname": "Label",
                  "name": "font",
                  "ZOrder": 0,
                  "actiontag": 54507558,
                  "anchorPointX": 0.5,
                  "anchorPointY": 0.5,
                  "classType": "CocoStudio.EngineAdapterWrap.CSLabel",
                  "colorB": 62,
                  "colorG": 89,
                  "colorR": 164,
                  "customProperty": "",
                  "flipX": false,
                  "flipY": false,
                  "height": 250,
                  "ignoreSize": false,
                  "layoutParameter": {
                    "classname": null,
                    "name": null,
                    "align": 1,
                    "gravity": 0,
                    "layoutEageType": 0,
                    "layoutNormalHorizontal": 0,
                    "layoutNormalVertical": 0,
                    "layoutParentHorizontal": 0,
                    "layoutParentVertical": 0,
                    "marginDown": 0,
                    "marginLeft": 298,
                    "marginRight": 0,
                    "marginTop": 68,
                    "relativeName": "font",
                    "relativeToName": "if_install",
                    "type": 2
                  },
                  "opacity": 255,
                  "positionPercentX": 0.623,
                  "positionPercentY": 0.5711111,
                  "positionType": 0,
                  "rotation": 0,
                  "scaleX": 1,
                  "scaleY": 1,
                  "sizePercentX": 0.65,
                  "sizePercentY": 0.5555556,
                  "sizeType": 0,
                  "tag": 5,
                  "touchAble": false,
                  "useMergedTexture": false,
                  "visible": true,
                  "width": 650,
                  "x": 623,
                  "y": 257,
                  "areaHeight": 250,
                  "areaWidth": 650,
                  "fontFile": null,
                  "fontName": "微软雅黑",
                  "fontSize": 40,
                  "hAlignment": 0,
                  "text": "Text Label",
                  "touchScaleEnable": false,
                  "vAlignment": 0
                }
              },
              {
                "classname": "Button",
                "name": null,
                "children": [
                  {
                    "classname": "ImageView",
                    "name": null,
                    "children": [],
                    "options": {
                      "__type": "ImageViewSurrogate:#EditorCommon.JsonModel.Component.GUI",
                      "classname": "ImageView",
                      "name": "Image_7",
                      "ZOrder": 0,
                      "actiontag": 25884632,
                      "anchorPointX": 0.5,
                      "anchorPointY": 0.5,
                      "classType": "CocoStudio.EngineAdapterWrap.CSImageView",
                      "colorB": 255,
                      "colorG": 255,
                      "colorR": 255,
                      "customProperty": "",
                      "flipX": false,
                      "flipY": false,
                      "height": 64,
                      "ignoreSize": true,
                      "layoutParameter": null,
                      "opacity": 255,
                      "positionPercentX": 0,
                      "positionPercentY": 0,
                      "positionType": 0,
                      "rotation": 0,
                      "scaleX": 1,
                      "scaleY": 1,
                      "sizePercentX": 0.379746825,
                      "sizePercentY": 0.470588237,
                      "sizeType": 0,
                      "tag": 8,
                      "touchAble": false,
                      "useMergedTexture": false,
                      "visible": true,
                      "width": 120,
                      "x": 0,
                      "y": 0,
                      "capInsetsHeight": 1,
                      "capInsetsWidth": 1,
                      "capInsetsX": 0,
                      "capInsetsY": 0,
                      "fileName": null,
                      "fileNameData": {
                        "path": "global/btn_normal_351x113_n01.png",
                        "plistFile": "",
                        "resourceType": 0
                      },
                      "scale9Enable": false,
                      "scale9Height": 64,
                      "scale9Width": 120
                    }
                  }
                ],
                "options": {
                  "__type": "ButtonSurrogate:#EditorCommon.JsonModel.Component.GUI",
                  "classname": "Button",
                  "name": "cancel",
                  "ZOrder": 0,
                  "actiontag": 53599109,
                  "anchorPointX": 0.5,
                  "anchorPointY": 0.5,
                  "classType": "CocoStudio.EngineAdapterWrap.CSButton",
                  "colorB": 255,
                  "colorG": 255,
                  "colorR": 255,
                  "customProperty": "",
                  "flipX": false,
                  "flipY": false,
                  "height": 136,
                  "ignoreSize": true,
                  "layoutParameter": {
                    "classname": null,
                    "name": null,
                    "align": 1,
                    "gravity": 0,
                    "layoutEageType": 0,
                    "layoutNormalHorizontal": 0,
                    "layoutNormalVertical": 0,
                    "layoutParentHorizontal": 0,
                    "layoutParentVertical": 0,
                    "marginDown": 0,
                    "marginLeft": 78,
                    "marginRight": 0,
                    "marginTop": 453,
                    "relativeName": "cancel",
                    "relativeToName": "if_install",
                    "type": 2
                  },
                  "opacity": 255,
                  "positionPercentX": 0.236,
                  "positionPercentY": -0.157777771,
                  "positionType": 0,
                  "rotation": 0,
                  "scaleX": 1,
                  "scaleY": 1,
                  "sizePercentX": 0.316,
                  "sizePercentY": 0.302222222,
                  "sizeType": 0,
                  "tag": 6,
                  "touchAble": true,
                  "useMergedTexture": false,
                  "visible": true,
                  "width": 316,
                  "x": 236,
                  "y": -71,
                  "capInsetsHeight": 1,
                  "capInsetsWidth": 1,
                  "capInsetsX": 0,
                  "capInsetsY": 0,
                  "disabled": null,
                  "disabledData": {
                    "path": null,
                    "plistFile": null,
                    "resourceType": 0
                  },
                  "fontName": "微软雅黑",
                  "fontSize": 14,
                  "fontType": 0,
                  "normal": null,
                  "normalData": {
                    "path": "global/btn_normal_351x113_n.png",
                    "plistFile": "",
                    "resourceType": 0
                  },
                  "pressed": null,
                  "pressedData": {
                    "path": null,
                    "plistFile": null,
                    "resourceType": 0
                  },
                  "scale9Enable": false,
                  "scale9Height": 136,
                  "scale9Width": 316,
                  "text": "",
                  "textColorB": 255,
                  "textColorG": 255,
                  "textColorR": 255
                }
              },
              {
                "classname": "Button",
                "name": null,
                "children": [
                  {
                    "classname": "ImageView",
                    "name": null,
                    "children": [],
                    "options": {
                      "__type": "ImageViewSurrogate:#EditorCommon.JsonModel.Component.GUI",
                      "classname": "ImageView",
                      "name": "Image_8",
                      "ZOrder": 0,
                      "actiontag": 22412087,
                      "anchorPointX": 0.5,
                      "anchorPointY": 0.5,
                      "classType": "CocoStudio.EngineAdapterWrap.CSImageView",
                      "colorB": 255,
                      "colorG": 255,
                      "colorR": 255,
                      "customProperty": "",
                      "flipX": false,
                      "flipY": false,
                      "height": 70,
                      "ignoreSize": true,
                      "layoutParameter": null,
                      "opacity": 255,
                      "positionPercentX": 0,
                      "positionPercentY": 0,
                      "positionType": 0,
                      "rotation": 0,
                      "scaleX": 1,
                      "scaleY": 1,
                      "sizePercentX": 0.401898742,
                      "sizePercentY": 0.5147059,
                      "sizeType": 0,
                      "tag": 9,
                      "touchAble": false,
                      "useMergedTexture": false,
                      "visible": true,
                      "width": 127,
                      "x": 0,
                      "y": 0,
                      "capInsetsHeight": 1,
                      "capInsetsWidth": 1,
                      "capInsetsX": 0,
                      "capInsetsY": 0,
                      "fileName": null,
                      "fileNameData": {
                        "path": "global/btn_normal_351x113_y01.png",
                        "plistFile": "",
                        "resourceType": 0
                      },
                      "scale9Enable": false,
                      "scale9Height": 70,
                      "scale9Width": 127
                    }
                  }
                ],
                "options": {
                  "__type": "ButtonSurrogate:#EditorCommon.JsonModel.Component.GUI",
                  "classname": "Button",
                  "name": "confirm",
                  "ZOrder": 0,
                  "actiontag": 35845618,
                  "anchorPointX": 0.5,
                  "anchorPointY": 0.5,
                  "classType": "CocoStudio.EngineAdapterWrap.CSButton",
                  "colorB": 255,
                  "colorG": 255,
                  "colorR": 255,
                  "customProperty": "",
                  "flipX": false,
                  "flipY": false,
                  "height": 136,
                  "ignoreSize": true,
                  "layoutParameter": {
                    "classname": null,
                    "name": null,
                    "align": 1,
                    "gravity": 0,
                    "layoutEageType": 0,
                    "layoutNormalHorizontal": 0,
                    "layoutNormalVertical": 0,
                    "layoutParentHorizontal": 0,
                    "layoutParentVertical": 0,
                    "marginDown": 0,
                    "marginLeft": 588,
                    "marginRight": 0,
                    "marginTop": 453,
                    "relativeName": "confirm",
                    "relativeToName": "if_install",
                    "type": 2
                  },
                  "opacity": 255,
                  "positionPercentX": 0.746,
                  "positionPercentY": -0.157777771,
                  "positionType": 0,
                  "rotation": 0,
                  "scaleX": 1,
                  "scaleY": 1,
                  "sizePercentX": 0.316,
                  "sizePercentY": 0.302222222,
                  "sizeType": 0,
                  "tag": 7,
                  "touchAble": true,
                  "useMergedTexture": false,
                  "visible": true,
                  "width": 316,
                  "x": 746,
                  "y": -71,
                  "capInsetsHeight": 1,
                  "capInsetsWidth": 1,
                  "capInsetsX": 0,
                  "capInsetsY": 0,
                  "disabled": null,
                  "disabledData": {
                    "path": null,
                    "plistFile": null,
                    "resourceType": 0
                  },
                  "fontName": "微软雅黑",
                  "fontSize": 14,
                  "fontType": 0,
                  "normal": null,
                  "normalData": {
                    "path": "global/btn_normal_351x113_y.png",
                    "plistFile": "",
                    "resourceType": 0
                  },
                  "pressed": null,
                  "pressedData": {
                    "path": null,
                    "plistFile": null,
                    "resourceType": 0
                  },
                  "scale9Enable": false,
                  "scale9Height": 136,
                  "scale9Width": 316,
                  "text": "",
                  "textColorB": 255,
                  "textColorG": 255,
                  "textColorR": 255
                }
              }
            ],
            "options": {
              "__type": "PanelSurrogate:#EditorCommon.JsonModel.Component.GUI",
              "classname": "Panel",
              "name": "if_install",
              "ZOrder": 0,
              "actiontag": 27578655,
              "anchorPointX": 0,
              "anchorPointY": 0,
              "classType": "CocoStudio.EngineAdapterWrap.CSPanel",
              "colorB": 255,
              "colorG": 255,
              "colorR": 255,
              "customProperty": "",
              "flipX": false,
              "flipY": false,
              "height": 450,
              "ignoreSize": false,
              "layoutParameter": {
                "classname": null,
                "name": null,
                "align": 2,
                "gravity": 0,
                "layoutEageType": 0,
                "layoutNormalHorizontal": 0,
                "layoutNormalVertical": 0,
                "layoutParentHorizontal": 0,
                "layoutParentVertical": 0,
                "marginDown": 0,
                "marginLeft": 0,
                "marginRight": 0,
                "marginTop": 120,
                "relativeName": "if_install",
                "relativeToName": "pop",
                "type": 2
              },
              "opacity": 255,
              "positionPercentX": 0.05277281,
              "positionPercentY": 0.21161826,
              "positionType": 0,
              "rotation": 0,
              "scaleX": 1,
              "scaleY": 1,
              "sizePercentX": 0.89445436,
              "sizePercentY": 0.622406662,
              "sizeType": 0,
              "tag": 13,
              "touchAble": true,
              "useMergedTexture": false,
              "visible": true,
              "width": 1000,
              "x": 59,
              "y": 153,
              "adaptScreen": false,
              "backGroundImage": null,
              "backGroundImageData": null,
              "backGroundScale9Enable": false,
              "bgColorB": 255,
              "bgColorG": 200,
              "bgColorOpacity": 0,
              "bgColorR": 150,
              "bgEndColorB": 255,
              "bgEndColorG": 200,
              "bgEndColorR": 150,
              "bgStartColorB": 255,
              "bgStartColorG": 255,
              "bgStartColorR": 255,
              "capInsetsHeight": 1,
              "capInsetsWidth": 1,
              "capInsetsX": 0,
              "capInsetsY": 0,
              "clipAble": false,
              "colorType": 1,
              "layoutType": 3,
              "vectorX": 0,
              "vectorY": -0.5
            }
          }
        ],
        "options": {
          "__type": "PanelSurrogate:#EditorCommon.JsonModel.Component.GUI",
          "classname": "Panel",
          "name": "pop",
          "ZOrder": 0,
          "actiontag": 58635765,
          "anchorPointX": 0,
          "anchorPointY": 0,
          "classType": "CocoStudio.EngineAdapterWrap.CSPanel",
          "colorB": 255,
          "colorG": 255,
          "colorR": 255,
          "customProperty": "",
          "flipX": false,
          "flipY": false,
          "height": 723,
          "ignoreSize": false,
          "layoutParameter": {
            "classname": null,
            "name": null,
            "align": 5,
            "gravity": 0,
            "layoutEageType": 0,
            "layoutNormalHorizontal": 0,
            "layoutNormalVertical": 0,
            "layoutParentHorizontal": 0,
            "layoutParentVertical": 0,
            "marginDown": 0,
            "marginLeft": 0,
            "marginRight": 0,
            "marginTop": 880,
            "relativeName": "pop",
            "relativeToName": "root",
            "type": 2
          },
          "opacity": 255,
          "positionPercentX": 0.208854169,
          "positionPercentY": 0.165277779,
          "positionType": 0,
          "rotation": 0,
          "scaleX": 1,
          "scaleY": 1,
          "sizePercentX": 0.582291663,
          "sizePercentY": 0.669444442,
          "sizeType": 0,
          "tag": 2,
          "touchAble": true,
          "useMergedTexture": false,
          "visible": true,
          "width": 1118,
          "x": 401,
          "y": 178,
          "adaptScreen": false,
          "backGroundImage": null,
          "backGroundImageData": {
            "path": "install/global_dialog_create_room.png",
            "plistFile": "",
            "resourceType": 0
          },
          "backGroundScale9Enable": false,
          "bgColorB": 255,
          "bgColorG": 200,
          "bgColorOpacity": 0,
          "bgColorR": 150,
          "bgEndColorB": 255,
          "bgEndColorG": 200,
          "bgEndColorR": 150,
          "bgStartColorB": 255,
          "bgStartColorG": 255,
          "bgStartColorR": 255,
          "capInsetsHeight": 1,
          "capInsetsWidth": 1,
          "capInsetsX": 0,
          "capInsetsY": 0,
          "clipAble": false,
          "colorType": 1,
          "layoutType": 3,
          "vectorX": 0,
          "vectorY": -0.5
        }
      }
    ],
    "options": {
      "__type": "PanelSurrogate:#EditorCommon.JsonModel.Component.GUI",
      "classname": "Panel",
      "name": "root",
      "ZOrder": 0,
      "actiontag": -1,
      "anchorPointX": 0,
      "anchorPointY": 0,
      "classType": "CocoStudio.EngineAdapterWrap.CSPanel",
      "colorB": 255,
      "colorG": 255,
      "colorR": 255,
      "customProperty": "",
      "flipX": false,
      "flipY": false,
      "height": 1080,
      "ignoreSize": false,
      "layoutParameter": null,
      "opacity": 255,
      "positionPercentX": 0,
      "positionPercentY": 0,
      "positionType": 0,
      "rotation": 0,
      "scaleX": 1,
      "scaleY": 1,
      "sizePercentX": 1,
      "sizePercentY": 1,
      "sizeType": 0,
      "tag": 1,
      "touchAble": true,
      "useMergedTexture": false,
      "visible": true,
      "width": 1920,
      "x": 0,
      "y": 0,
      "adaptScreen": true,
      "backGroundImage": null,
      "backGroundImageData": null,
      "backGroundScale9Enable": false,
      "bgColorB": 255,
      "bgColorG": 200,
      "bgColorOpacity": 0,
      "bgColorR": 150,
      "bgEndColorB": 255,
      "bgEndColorG": 200,
      "bgEndColorR": 150,
      "bgStartColorB": 255,
      "bgStartColorG": 255,
      "bgStartColorR": 255,
      "capInsetsHeight": 1,
      "capInsetsWidth": 1,
      "capInsetsX": 0,
      "capInsetsY": 0,
      "clipAble": false,
      "colorType": 1,
      "layoutType": 3,
      "vectorX": 0,
      "vectorY": -0.5
    }
  }
}  